gpuinfo/GPUInfo.py
gpuinfo/__init__.py
gpuinfo-1.0.0a7.dist-info/LICENSE.txt
gpuinfo-1.0.0a7.dist-info/METADATA
gpuinfo-1.0.0a7.dist-info/WHEEL
gpuinfo-1.0.0a7.dist-info/top_level.txt
gpuinfo-1.0.0a7.dist-info/RECORD
