Metadata-Version: 2.1
Name: gpuinfo
Version: 1.0.0a7
Summary: A quick access to nvidia gpu information
Home-page: UNKNOWN
Author: Zhang Tianyu
Author-email: tyz.xyz@qq.com
License: UNKNOWN
Project-URL: Source, https://github.com/FlyHighest/gpuinfo/
Keywords: gpu information
Platform: UNKNOWN
Classifier: Development Status :: 3 - Alpha
Classifier: Intended Audience :: Developers
Classifier: License :: OSI Approved :: MIT License
Classifier: Programming Language :: Python :: 3
